dbtui/__about__.py
dbtui/__init__.py
dbtui/__main__.py
dbtui/cli.py
dbtui/loader.py
dbtui/schemas.py
dbtui-0.0.2.dist-info/METADATA
dbtui-0.0.2.dist-info/WHEEL
dbtui-0.0.2.dist-info/entry_points.txt
dbtui-0.0.2.dist-info/licenses/LICENSE
dbtui-0.0.2.dist-info/RECORD
